etc/pyquarantine/pyquarantine.conf.default
etc/pyquarantine/templates/disclaimer_html.template
etc/pyquarantine/templates/disclaimer_text.template
etc/pyquarantine/templates/notification.template
etc/pyquarantine/templates/removed.png
pyquarantine/__init__.py
pyquarantine/_install.py
pyquarantine/_runtime_patches.py
pyquarantine/action.py
pyquarantine/base.py
pyquarantine/cli.py
pyquarantine/conditions.py
pyquarantine/config.py
pyquarantine/lists.py
pyquarantine/mailer.py
pyquarantine/modify.py
pyquarantine/notify.py
pyquarantine/rule.py
pyquarantine/run.py
pyquarantine/storage.py
pyquarantine/whitelist.py
pyquarantine/misc/pyquarantine.conf.default
pyquarantine/misc/openrc/pyquarantine-milter.confd
pyquarantine/misc/openrc/pyquarantine-milter.initd
pyquarantine/misc/systemd/pyquarantine-milter.service
pyquarantine/misc/templates/disclaimer_html.template
pyquarantine/misc/templates/disclaimer_text.template
pyquarantine/misc/templates/notification.template
pyquarantine/misc/templates/removed.png
pyquarantine-2.1.0.dist-info/LICENSE
pyquarantine-2.1.0.dist-info/METADATA
pyquarantine-2.1.0.dist-info/WHEEL
pyquarantine-2.1.0.dist-info/entry_points.txt
pyquarantine-2.1.0.dist-info/top_level.txt
pyquarantine-2.1.0.dist-info/RECORD
