Metadata-Version: 2.1
Name: pyquarantine
Version: 2.1.0
Summary: A pymilter based sendmail/postfix pre-queue filter.
Home-page: https://github.com/spacefreak86/pyquarantine
Author: Thomas Oettli
Author-email: spacefreak@noop.ch
License: GPL 3
Keywords: header quarantine milter
Classifier: Development Status :: 5 - Production/Stable
Classifier: License :: OSI Approved :: GNU General Public License v3 or later (GPLv3+)
Classifier: Operating System :: OS Independent
Classifier: Programming Language :: Python
Classifier: Programming Language :: Python :: 3
Classifier: Topic :: Communications :: Email :: Filters
Requires-Python: >=3.10
License-File: LICENSE
Requires-Dist: pymilter >=1.5
Requires-Dist: jsonschema
Requires-Dist: netaddr
Requires-Dist: beautifulsoup4[lxml]
Requires-Dist: peewee
